nexd/__init__.py
nexd/main.py
nexd-1.3.2.data/scripts/main.py
nexd-1.3.2.dist-info/LICENSE
nexd-1.3.2.dist-info/METADATA
nexd-1.3.2.dist-info/WHEEL
nexd-1.3.2.dist-info/top_level.txt
nexd-1.3.2.dist-info/RECORD
