Metadata-Version: 2.1
Name: nexd
Version: 1.3.2
Summary: Ma librairie de fonctions utiles
Home-page: https://github.com/importFourmi/nexd
Author: importFourmi
Author-email: calvin.galagain@gmail.com
Classifier: Programming Language :: Python :: 3
License-File: LICENSE
Requires-Dist: opencv-python
Requires-Dist: matplotlib
Requires-Dist: numpy
Requires-Dist: scikit-learn
